erp_xm_kt_cbase.cp310-win_amd64.pyd
erp_xm_kt_cbase-1.0.2.dist-info/LICENSE
erp_xm_kt_cbase-1.0.2.dist-info/METADATA
erp_xm_kt_cbase-1.0.2.dist-info/WHEEL
erp_xm_kt_cbase-1.0.2.dist-info/top_level.txt
erp_xm_kt_cbase-1.0.2.dist-info/RECORD
