Metadata-Version: 2.1
Name: erp-xm-kt-cbase
Version: 1.0.2
Summary: utils for xw
Home-page: https://www.openerpenext.com/
Author: xw odoo
Author-email: 2243879204@qq.com
Requires-Python: >=3.7
License-File: LICENSE
